uvitility/__init__.py
uvitility/uvitility.py
uvitility-0.1.4.dist-info/licenses/LICENSE
uvitility-0.1.4.dist-info/METADATA
uvitility-0.1.4.dist-info/WHEEL
uvitility-0.1.4.dist-info/top_level.txt
uvitility-0.1.4.dist-info/RECORD
