Metadata-Version: 2.4
Name: uvitility
Version: 0.1.4
Summary: UVIT utility functions
Home-page: https://github.com/prajwel/uvitility
Author: Prajwel Joseph
Author-email: prajwel.pj@gmail.com
License: Apache-2.0
Project-URL: Bug Tracker, https://github.com/prajwel/uvitility/issues
Classifier: Programming Language :: Python :: 3
Classifier: Operating System :: OS Independent
Requires-Python: >=3.6
License-File: LICENSE
Requires-Dist: numpy>=1.13
Requires-Dist: matplotlib>=2
Requires-Dist: astropy>=2
Dynamic: license-file
